Workbook

Sheet Inputs
A1: Interest rate swap valuation, curve date 2024-12-31
A3: Pillar (years) | B3: Treasury par yield (%) | C3: Zero rate used (decimal)
A4: 0.5 | B4: 4.24 | C4: =B4/100 -> 0.0424
A5: 1 | B5: 4.16 | C5: =B5/100 -> 0.0416
A6: 2 | B6: 4.25 | C6: =B6/100 -> 0.0425
A7: 3 | B7: 4.27 | C7: =B7/100 -> 0.0427
A9: Notional (USD) | B9: 10000000
A10: Swap fixed rate K (pay fixed) | B10: 0.04
A11: Payment frequency tau (years) | B11: 0.5
A12: Parallel bump for DV01 (bp) | B12: 1
A13: USD/JPY spot (FRED DEXJPUS) | B13: 157.37
A14: USD leg fixed rate (cross-currency) | B14: 0.04
A15: JPY leg fixed rate (cross-currency) | B15: 0.01
A16: JPY flat discount rate (assumption) | B16: 0.007
A18: Treasury par yields are used as a continuously compounded zero-curve proxy (a simplification). SOFR OIS pillars would be the production input.
A19: The 1.5Y and 2.5Y points are linear averages of neighbouring pillars. The JPY discount rate and JPY coupon are illustrative assumptions.

Sheet Swap_Valuation
A1: 3-year semiannual pay-fixed swap on SOFR-style floating, curve-discounted
A3: Period | B3: Time t | C3: Zero rate | D3: Discount factor | E3: Fixed CF | F3: Forward rate | G3: Floating CF | H3: Zero (bumped) | I3: DF (bumped) | J3: Fixed CF (bumped) | K3: Forward (bumped) | L3: Floating CF (bumped)
A4: 1 | B4: 0.5 | C4: =Inputs!C4 -> 0.0424 | D4: =EXP(-C4*B4) -> 0.97902314 | E4: =Inputs!$B$10*Inputs!$B$11*Inputs!$B$9 -> 200000 | F4: =(1/D4-1)/Inputs!$B$11 -> 0.042852633 | G4: =F4*Inputs!$B$11*Inputs!$B$9 -> 214263.16 | H4: =C4+Inputs!$B$12/10000 -> 0.0425 | I4: =EXP(-H4*B4) -> 0.97897419 | J4: =Inputs!$B$10*Inputs!$B$11*Inputs!$B$9 -> 200000 | K4: =(1/I4-1)/Inputs!$B$11 -> 0.042954778 | L4: =K4*Inputs!$B$11*Inputs!$B$9 -> 214773.89
A5: 2 | B5: 1 | C5: =Inputs!C5 -> 0.0416 | D5: =EXP(-C5*B5) -> 0.95925341 | E5: =Inputs!$B$10*Inputs!$B$11*Inputs!$B$9 -> 200000 | F5: =(D4/D5-1)/Inputs!$B$11 -> 0.041219004 | G5: =F5*Inputs!$B$11*Inputs!$B$9 -> 206095.02 | H5: =C5+Inputs!$B$12/10000 -> 0.0417 | I5: =EXP(-H5*B5) -> 0.95915748 | J5: =Inputs!$B$10*Inputs!$B$11*Inputs!$B$9 -> 200000 | K5: =(I4/I5-1)/Inputs!$B$11 -> 0.041321068 | L5: =K5*Inputs!$B$11*Inputs!$B$9 -> 206605.34
A6: 3 | B6: 1.5 | C6: =(Inputs!C5+Inputs!C6)/2 -> 0.04205 | D6: =EXP(-C6*B6) -> 0.93887306 | E6: =Inputs!$B$10*Inputs!$B$11*Inputs!$B$9 -> 200000 | F6: =(D5/D6-1)/Inputs!$B$11 -> 0.043414495 | G6: =F6*Inputs!$B$11*Inputs!$B$9 -> 217072.47 | H6: =C6+Inputs!$B$12/10000 -> 0.04215 | I6: =EXP(-H6*B6) -> 0.93873224 | J6: =Inputs!$B$10*Inputs!$B$11*Inputs!$B$9 -> 200000 | K6: =(I5/I6-1)/Inputs!$B$11 -> 0.043516668 | L6: =K6*Inputs!$B$11*Inputs!$B$9 -> 217583.34
A7: 4 | B7: 2 | C7: =Inputs!C6 -> 0.0425 | D7: =EXP(-C7*B7) -> 0.91851228 | E7: =Inputs!$B$10*Inputs!$B$11*Inputs!$B$9 -> 200000 | F7: =(D6/D7-1)/Inputs!$B$11 -> 0.044334238 | G7: =F7*Inputs!$B$11*Inputs!$B$9 -> 221671.19 | H7: =C7+Inputs!$B$12/10000 -> 0.0426 | I7: =EXP(-H7*B7) -> 0.9183286 | J7: =Inputs!$B$10*Inputs!$B$11*Inputs!$B$9 -> 200000 | K7: =(I6/I7-1)/Inputs!$B$11 -> 0.044436457 | L7: =K7*Inputs!$B$11*Inputs!$B$9 -> 222182.29
A8: 5 | B8: 2.5 | C8: =(Inputs!C6+Inputs!C7)/2 -> 0.0426 | D8: =EXP(-C8*B8) -> 0.89897505 | E8: =Inputs!$B$10*Inputs!$B$11*Inputs!$B$9 -> 200000 | F8: =(D7/D8-1)/Inputs!$B$11 -> 0.043465581 | G8: =F8*Inputs!$B$11*Inputs!$B$9 -> 217327.9 | H8: =C8+Inputs!$B$12/10000 -> 0.0427 | I8: =EXP(-H8*B8) -> 0.89875033 | J8: =Inputs!$B$10*Inputs!$B$11*Inputs!$B$9 -> 200000 | K8: =(I7/I8-1)/Inputs!$B$11 -> 0.043567757 | L8: =K8*Inputs!$B$11*Inputs!$B$9 -> 217838.78
A9: 6 | B9: 3 | C9: =Inputs!C7 -> 0.0427 | D9: =EXP(-C9*B9) -> 0.8797654 | E9: =Inputs!$B$10*Inputs!$B$11*Inputs!$B$9 -> 200000 | F9: =(D8/D9-1)/Inputs!$B$11 -> 0.043669937 | G9: =F9*Inputs!$B$11*Inputs!$B$9 -> 218349.69 | H9: =C9+Inputs!$B$12/10000 -> 0.0428 | I9: =EXP(-H9*B9) -> 0.87950151 | J9: =Inputs!$B$10*Inputs!$B$11*Inputs!$B$9 -> 200000 | K9: =(I8/I9-1)/Inputs!$B$11 -> 0.043772124 | L9: =K9*Inputs!$B$11*Inputs!$B$9 -> 218860.62
A12: PV fixed leg | B12: =SUMPRODUCT(D4:D9,E4:E9) -> 1114880.5
A13: PV floating leg (forward-rate method) | B13: =SUMPRODUCT(D4:D9,G4:G9) -> 1202346
A14: PV floating leg (bond method: N x (1 - DF_N)) | B14: =Inputs!B9*(1-D9) -> 1202346
A15: Method check (should be 0) | B15: =B13-B14 -> 0
A16: Par swap rate | B16: =(1-D9)/(Inputs!B11*SUM(D4:D9)) -> 0.043138114
A17: Swap value to fixed payer (floating minus fixed) | B17: =B13-B12 -> 87465.552
A18: Swap value (bumped curve) | B18: =SUMPRODUCT(I4:I9,L4:L9)-SUMPRODUCT(I4:I9,J4:J9) -> 90296.048
A19: DV01 (value change per +1bp parallel) | B19: =B18-B17 -> 2830.4965
A20: Annuity (sum tau x DF) | B20: =Inputs!B11*SUM(D4:D9) -> 2.7872012

Sheet CrossCurrency
A1: Fixed-for-fixed USD/JPY cross-currency swap: pay USD fixed, receive JPY fixed, with final notional exchange
A3: USD notional | B3: =Inputs!B9 -> 10000000
A4: JPY notional (USD notional x spot) | B4: =B3*Inputs!B13 -> 1573700000
A6: Time t | B6: USD DF (curve) | C6: USD cash flow | D6: JPY DF (flat) | E6: JPY cash flow (yen)
A7: =Swap_Valuation!B4 -> 0.5 | B7: =Swap_Valuation!D4 -> 0.97902314 | C7: =$B$3*Inputs!$B$14*Inputs!$B$11 -> 200000 | D7: =EXP(-Inputs!$B$16*A7) -> 0.99650612 | E7: =$B$4*Inputs!$B$15*Inputs!$B$11 -> 7868500
A8: =Swap_Valuation!B5 -> 1 | B8: =Swap_Valuation!D5 -> 0.95925341 | C8: =$B$3*Inputs!$B$14*Inputs!$B$11 -> 200000 | D8: =EXP(-Inputs!$B$16*A8) -> 0.99302444 | E8: =$B$4*Inputs!$B$15*Inputs!$B$11 -> 7868500
A9: =Swap_Valuation!B6 -> 1.5 | B9: =Swap_Valuation!D6 -> 0.93887306 | C9: =$B$3*Inputs!$B$14*Inputs!$B$11 -> 200000 | D9: =EXP(-Inputs!$B$16*A9) -> 0.98955493 | E9: =$B$4*Inputs!$B$15*Inputs!$B$11 -> 7868500
A10: =Swap_Valuation!B7 -> 2 | B10: =Swap_Valuation!D7 -> 0.91851228 | C10: =$B$3*Inputs!$B$14*Inputs!$B$11 -> 200000 | D10: =EXP(-Inputs!$B$16*A10) -> 0.98609754 | E10: =$B$4*Inputs!$B$15*Inputs!$B$11 -> 7868500
A11: =Swap_Valuation!B8 -> 2.5 | B11: =Swap_Valuation!D8 -> 0.89897505 | C11: =$B$3*Inputs!$B$14*Inputs!$B$11 -> 200000 | D11: =EXP(-Inputs!$B$16*A11) -> 0.98265224 | E11: =$B$4*Inputs!$B$15*Inputs!$B$11 -> 7868500
A12: =Swap_Valuation!B9 -> 3 | B12: =Swap_Valuation!D9 -> 0.8797654 | C12: =$B$3*Inputs!$B$14*Inputs!$B$11+$B$3 -> 10200000 | D12: =EXP(-Inputs!$B$16*A12) -> 0.97921896 | E12: =$B$4*Inputs!$B$15*Inputs!$B$11+$B$4 -> 1581568500
A14: PV of USD bond (USD) | B14: =SUMPRODUCT(B7:B12,C7:C12) -> 9912534.4
A15: PV of JPY bond (yen) | B15: =SUMPRODUCT(D7:D12,E7:E12) -> 1.5876339e+09
A16: PV of JPY bond converted to USD | B16: =B15/Inputs!B13 -> 10088542
A17: Swap value (pay USD, receive JPY), USD | B17: =B16-B14 -> 176007.91
